whisperx/SubtitlesProcessor.py
whisperx/__init__.py
whisperx/__main__.py
whisperx/alignment.py
whisperx/asr.py
whisperx/audio.py
whisperx/conjunctions.py
whisperx/diarize.py
whisperx/transcribe.py
whisperx/types.py
whisperx/utils.py
whisperx/assets/mel_filters.npz
whisperx/assets/pytorch_model.bin
whisperx/vads/__init__.py
whisperx/vads/pyannote.py
whisperx/vads/silero.py
whisperx/vads/vad.py
whisperx_typed-3.4.5.dist-info/licenses/LICENSE
whisperx_typed-3.4.5.dist-info/METADATA
whisperx_typed-3.4.5.dist-info/WHEEL
whisperx_typed-3.4.5.dist-info/entry_points.txt
whisperx_typed-3.4.5.dist-info/top_level.txt
whisperx_typed-3.4.5.dist-info/RECORD
